README.md
setup.cfg
setup.py
qa_data_manager/__init__.py
qa_data_manager/appointment.py
qa_data_manager/bind_clinic_user.py
qa_data_manager/bind_doctor_information.py
qa_data_manager/bind_doctor_patient.py
qa_data_manager/bind_doctor_specialties.py
qa_data_manager/bind_family_accounts.py
qa_data_manager/chat.py
qa_data_manager/clinic.py
qa_data_manager/clinic_token.py
qa_data_manager/conclusion.py
qa_data_manager/config.py
qa_data_manager/consultation.py
qa_data_manager/data_base_model.py
qa_data_manager/db_generation.py
qa_data_manager/db_manager.py
qa_data_manager/db_requests.py
qa_data_manager/file.py
qa_data_manager/invoice.py
qa_data_manager/jwt_clinic_token.py
qa_data_manager/jwt_user_token.py
qa_data_manager/patient_problem.py
qa_data_manager/patient_problem_discomfort.py
qa_data_manager/patient_problem_slot_patient.py
qa_data_manager/payment.py
qa_data_manager/recommended_consultation.py
qa_data_manager/service.py
qa_data_manager/service_patient.py
qa_data_manager/skinive.py
qa_data_manager/slot_doctor.py
qa_data_manager/slot_doctor_patient.py
qa_data_manager/slots_doctors_patients_file.py
qa_data_manager/tracks.py
qa_data_manager/user.py
qa_data_manager/user_token.py
qa_data_manager.egg-info/PKG-INFO
qa_data_manager.egg-info/SOURCES.txt
qa_data_manager.egg-info/dependency_links.txt
qa_data_manager.egg-info/requires.txt
qa_data_manager.egg-info/top_level.txt