Metadata-Version: 2.1
Name: qa-data-manager
Version: 2.1.5
Summary: QA-DATA-MANAGER Генерация тестовых данных
Home-page: https://bitbucket.org/ibolitpro/qa-data-manager
Author: e.kurdyumov
Author-email: e.kurdyumov@ibolit.pro
